topsis/__init__.py
topsis/topsis.py
Topsis_Gazal_102217174-0.3.dist-info/METADATA
Topsis_Gazal_102217174-0.3.dist-info/WHEEL
Topsis_Gazal_102217174-0.3.dist-info/entry_points.txt
Topsis_Gazal_102217174-0.3.dist-info/top_level.txt
Topsis_Gazal_102217174-0.3.dist-info/RECORD
