Metadata-Version: 2.2
Name: Topsis-Gazal-102217174
Version: 0.3
Summary: A Python implementation of the TOPSIS method.
Author: Gazal
Author-email: 2580gazal@gmail.com
Requires-Dist: pandas
Requires-Dist: numpy
Requires-Dist: sys
Dynamic: author
Dynamic: author-email
Dynamic: description
Dynamic: description-content-type
Dynamic: requires-dist
Dynamic: summary
